controllers/main_controller.py
controllers/translation_controller.py
d_units_translation/pipeline.py
data_loaders/csv_data_loader.py
data_loaders/hugging_face_data_loader.py
data_loaders/json_data_loader.py
data_loaders/jsonl_data_loader.py
data_loaders/xml_tml_data_loader.py
dispatchers/load_data_dispatcher.py
dispatchers/translate_dispatcher.py
translation/deepl_translation.py
translation/hg_pipeline_translate_entry.py
utils/backup_utils.py
utils/config_utils.py
utils/correction_utils.py
utils/directory_utils.py
utils/file_utils.py
utils/logging_utils.py
utils/processing_utils.py
d_units_translation-0.1.2.dist-info/METADATA
d_units_translation-0.1.2.dist-info/WHEEL
d_units_translation-0.1.2.dist-info/entry_points.txt
d_units_translation-0.1.2.dist-info/top_level.txt
d_units_translation-0.1.2.dist-info/RECORD
