Metadata-Version: 2.4
Name: d-units-translation
Version: 0.1.2
Summary: A robust translating pipeline for multi-file support and integration with multiple translation sources.
Author-email: José Soares <jose.p.soares@inesctec.pt>
License-Expression: MIT
Project-URL: Homepage, https://github.com/YourUsername/TranslationPipeline
Keywords: translation,nlp,huggingface,deep-learning,dataset-processing
Requires-Python: >=3.10
Requires-Dist: datasets>=2.18.0
Requires-Dist: deep-translator>=1.11.4
Requires-Dist: ijson>=3.4.0
Requires-Dist: transformers>=4.57.0
Requires-Dist: torch>=2.8.0
